10minutemail.py
endpoints.py
minmail.py
minutemail.py
10minutemail/__init__.py
10minutemail/__main__.py
python_10minutemail-0.1.1.dist-info/LICENSE.md
python_10minutemail-0.1.1.dist-info/METADATA
python_10minutemail-0.1.1.dist-info/WHEEL
python_10minutemail-0.1.1.dist-info/top_level.txt
python_10minutemail-0.1.1.dist-info/RECORD
