Metadata-Version: 2.1
Name: python-10minutemail
Version: 0.1.1
Summary: Python wrapper for 10minutemail.com
Home-page: https://github.com/SauravKanchan/10minutemail
Author: Saurav Kanchan
Author-email: sauravnk30@gmail.com
License: MIT
Platform: UNKNOWN
Classifier: License :: OSI Approved :: MIT License
Classifier: Programming Language :: Python :: 3.6
Classifier: Programming Language :: Python :: 3.7
Classifier: Programming Language :: Python :: 3.8
Classifier: Programming Language :: Python :: 3.9
Requires-Dist: requests (>=2.20)
Provides-Extra: dev
Requires-Dist: pytest ; extra == 'dev'
Requires-Dist: tox ; extra == 'dev'
